surveymonkey/__init__.py
surveymonkey/client.py
surveymonkey/exceptions.py
surveymonkey_python-0.1.6.dist-info/LICENSE
surveymonkey_python-0.1.6.dist-info/METADATA
surveymonkey_python-0.1.6.dist-info/WHEEL
surveymonkey_python-0.1.6.dist-info/RECORD
